[
  {
    "id": 1,
    "date": 20250601,
    "title": "Mauris lacinia rutrum gravida. Vivamus felis nulla.",
    "content": "Nam rutrum pharetra consequat. Donec consectetur pellentesque rutrum. In aliquam semper est sed aliquam. Nulla vitae risus convallis, consectetur velit ut, condimentum nunc. Etiam lacinia, nisi nec porttitor maximus, diam lacus facilisis magna, vitae vulputate mi sem vitae magna. Ut fringilla pulvinar mauris, ac tincidunt magna hendrerit condimentum. Quisque sagittis libero vel convallis sodales. Sed nec viverra tortor. Praesent quam lorem, imperdiet vitae convallis sed, sollicitudin quis est. Fusce sit amet ullamcorper justo. Praesent tempor nisl et nunc egestas blandit. Curabitur sagittis elit quis orci varius, eget eleifend neque tincidunt. Vivamus blandit condimentum risus sagittis ornare. Integer imperdiet iaculis magna et viverra. In sed porttitor ligula. Suspendisse lacinia mi vitae metus tempor, a sollicitudin nisi vulputate.\nVestibulum laoreet massa in mi iaculis, ac molestie ante sollicitudin. Proin fermentum at lorem sed laoreet. Sed semper leo eros, in venenatis dolor varius vel. Suspendisse vel turpis et neque luctus porttitor nec in velit. Mauris ut ipsum venenatis, cursus velit vitae, porttitor mi. Vivamus at arcu vel nisl iaculis pellentesque. Etiam vitae dapibus sapien, quis dapibus lorem. Nulla bibendum condimentum dignissim. Ut ultricies lectus vulputate, finibus quam et, euismod enim. Donec aliquet, tellus sit amet commodo sodales, dui tellus porta nunc, non placerat lacus ligula vitae nulla. Suspendisse elementum, metus in vulputate auctor, urna lacus blandit risus, a placerat augue quam eget odio. Morbi convallis condimentum purus, at porttitor ante hendrerit at.\nMaecenas iaculis volutpat turpis, sed congue lacus tincidunt ac. Nulla non tellus laoreet ligula sodales finibus. Proin eget tortor in massa posuere commodo nec nec mauris. Cras in purus eu justo sodales lacinia. Maecenas feugiat justo a sem convallis viverra. Donec a gravida sem, eu maximus leo. Integer quis ex vitae velit auctor tincidunt. Curabitur ut velit eros. Nunc efficitur accumsan dictum. Vestibulum vehicula nulla nec erat ultrices, ut varius massa rutrum. Integer vehicula, ipsum sed laoreet euismod, orci nulla euismod eros, eget pulvinar arcu lacus in odio. Nam a ligula luctus, consectetur arcu nec, egestas ante. Donec in vulputate diam. Sed porta odio et gravida cursus. Sed ut pharetra leo.\nSuspendisse a malesuada dolor, sit amet bibendum risus. Donec ut porttitor massa. Sed faucibus congue ipsum quis efficitur. Suspendisse posuere malesuada posuere. Nulla commodo erat et cursus vehicula. Quisque tempor metus ac turpis placerat tempor. Fusce ex leo, aliquam vitae rutrum ut, mattis eget purus. Nunc a aliquet enim. Praesent tincidunt sollicitudin tincidunt. Duis luctus ligula urna, sed tincidunt est semper nec. Suspendisse potenti. Duis nec dolor feugiat, commodo ipsum non, hendrerit quam.\nMorbi quis fringilla erat. Proin pharetra tortor quis enim facilisis auctor. Vestibulum eget ultricies diam, sed tristique odio. Nulla nibh diam, congue nec viverra a, rutrum sit amet magna. Sed ac velit sed mauris volutpat tincidunt. Aliquam malesuada risus ac lectus tristique, vitae cursus eros pulvinar. Etiam sit amet erat semper, bibendum quam sed, porttitor justo.\nMaecenas mi quam, euismod at ullamcorper ut, commodo at quam. Morbi dictum ligula ut malesuada tincidunt. Proin volutpat, urna sit amet commodo imperdiet, diam urna bibendum dui, non finibus leo diam id eros. Quisque iaculis massa et massa feugiat auctor. Vivamus nec accumsan magna. Quisque in interdum eros. Praesent dolor massa, convallis id pharetra eu, congue et eros. Proin facilisis vehicula sapien dignissim condimentum.\nPhasellus non mi ut ante pretium congue ut vel lacus. Suspendisse potenti. Etiam quis justo laoreet, porttitor quam eget, varius nunc. Nam quis tortor enim. Nunc vehicula a erat vitae semper. Aliquam laoreet dignissim feugiat. Morbi eleifend cursus suscipit. Proin vestibulum vestibulum nibh, sed egestas nibh luctus eget. Sed facilisis eros luctus, volutpat sem at, porttitor felis. Nam placerat eleifend leo et tempor. Proin a ligula eleifend erat hendrerit suscipit a et magna. Suspendisse potenti. Quisque sollicitudin turpis sed ornare euismod. Aliquam molestie sed magna id volutpat. Nullam at cursus lacus, id consectetur nulla. Fusce rutrum laoreet ligula tempor dignissim."
  },
  {
    "id": 2,
    "date": 20250612,
    "title": "Quisque et urna at nunc.",
    "content": "Ut ornare et urna sed vehicula. Duis non egestas libero. Phasellus dolor nulla, viverra ut ex eget, posuere eleifend purus. Morbi neque nunc, sagittis eget iaculis sit amet, condimentum quis lorem. Aenean eu lorem lorem. Vestibulum ante ipsum primis in faucibus orci luctus et ultrices posuere cubilia curae; Nulla tellus purus, venenatis vel ante vitae, sollicitudin vehicula nisl. Suspendisse condimentum molestie ligula et finibus. Donec erat elit, mollis et quam nec, pretium efficitur purus. Phasellus erat dui, volutpat quis urna in, ornare aliquam libero. Proin efficitur non sapien ac aliquam.\nSuspendisse varius aliquam lorem ut feugiat. Phasellus at nisl tristique, tempor ante at, interdum mi. Sed vel nulla est. Donec porttitor varius porttitor. Phasellus fermentum, mauris et iaculis aliquam, arcu nulla tincidunt leo, hendrerit laoreet massa est sit amet purus. Vestibulum vulputate volutpat pellentesque. Maecenas varius ultrices lorem. In hac habitasse platea dictumst. Vivamus vestibulum sed nulla ut scelerisque.\nFusce pulvinar, quam id interdum pretium, arcu mauris maximus nibh, ut malesuada arcu nunc ut justo. Suspendisse molestie consequat diam, quis lobortis lacus aliquam facilisis. Sed risus erat, ullamcorper vel tincidunt nec, sodales et erat. Ut fringilla posuere nisl mollis rutrum. Nullam vitae feugiat tellus, sit amet pretium quam. Suspendisse malesuada dapibus mauris, ac gravida ex. Aliquam at rutrum odio. Suspendisse commodo massa sit amet massa pellentesque congue. In rhoncus fermentum risus sed consequat. Duis et felis ut ipsum commodo tristique rutrum non ipsum. Phasellus placerat ac neque a blandit. Sed vel ornare magna, quis feugiat odio. Phasellus aliquam lorem quis aliquam finibus. Duis vestibulum in sem iaculis iaculis.\nPhasellus pulvinar enim sed convallis dignissim. Nunc dictum urna dolor, in pellentesque mi efficitur ut. Maecenas id justo et orci placerat ultricies blandit eu nibh. Nunc non vehicula ex, porttitor aliquet enim. Quisque eu erat tincidunt, malesuada orci vel, convallis purus. Nulla molestie egestas fringilla. Donec id eros id tellus molestie interdum a eget urna. Etiam placerat, nibh et tristique ultricies, augue odio consequat diam, id rutrum nibh tortor ac felis. Praesent ac consectetur enim. Aenean ultricies felis viverra ipsum mattis, ut auctor nunc lacinia. Quisque at pulvinar nulla. Cras quis diam ac arcu ornare aliquet. Integer at lectus eu lorem iaculis luctus sed eget risus. Curabitur accumsan quam ante, eu luctus neque pulvinar sit amet. Vestibulum rhoncus tincidunt volutpat. Ut mollis nisl leo, id pretium tortor sollicitudin non.\nNulla lectus neque, iaculis et commodo eu, ultricies vitae lectus. Ut in dolor interdum, eleifend turpis ac, auctor augue. Praesent at dapibus sem. Fusce et dui eu nunc feugiat porta vitae eget leo. Integer a efficitur risus, ac dictum sapien. Ut magna purus, sodales et consectetur eget, luctus ac est. Praesent ultrices arcu at magna tincidunt egestas. Mauris luctus semper enim at consectetur. Vestibulum et auctor mauris, ac mattis libero. Nam eu rutrum purus. Integer vel tellus vel turpis malesuada pharetra non eu massa. Duis molestie orci accumsan lectus congue, vel ullamcorper metus gravida. Sed vitae luctus velit. Cras dolor risus, luctus nec imperdiet vel, egestas a mi."
  },
  {
    "id": 3,
    "date": 20250618,
    "title": "Curabitur ipsum urna, sollicitudin nec suscipit.",
    "content": "Nam rutrum pharetra consequat. Donec consectetur pellentesque rutrum. In aliquam semper est sed aliquam. Nulla vitae risus convallis, consectetur velit ut, condimentum nunc. Etiam lacinia, nisi nec porttitor maximus, diam lacus facilisis magna, vitae vulputate mi sem vitae magna. Ut fringilla pulvinar mauris, ac tincidunt magna hendrerit condimentum. Quisque sagittis libero vel convallis sodales. Sed nec viverra tortor. Praesent quam lorem, imperdiet vitae convallis sed, sollicitudin quis est. Fusce sit amet ullamcorper justo. Praesent tempor nisl et nunc egestas blandit. Curabitur sagittis elit quis orci varius, eget eleifend neque tincidunt. Vivamus blandit condimentum risus sagittis ornare. Integer imperdiet iaculis magna et viverra. In sed porttitor ligula. Suspendisse lacinia mi vitae metus tempor, a sollicitudin nisi vulputate.\nVestibulum laoreet massa in mi iaculis, ac molestie ante sollicitudin. Proin fermentum at lorem sed laoreet. Sed semper leo eros, in venenatis dolor varius vel. Suspendisse vel turpis et neque luctus porttitor nec in velit. Mauris ut ipsum venenatis, cursus velit vitae, porttitor mi. Vivamus at arcu vel nisl iaculis pellentesque. Etiam vitae dapibus sapien, quis dapibus lorem. Nulla bibendum condimentum dignissim. Ut ultricies lectus vulputate, finibus quam et, euismod enim. Donec aliquet, tellus sit amet commodo sodales, dui tellus porta nunc, non placerat lacus ligula vitae nulla. Suspendisse elementum, metus in vulputate auctor, urna lacus blandit risus, a placerat augue quam eget odio. Morbi convallis condimentum purus, at porttitor ante hendrerit at.\nMaecenas iaculis volutpat turpis, sed congue lacus tincidunt ac. Nulla non tellus laoreet ligula sodales finibus. Proin eget tortor in massa posuere commodo nec nec mauris. Cras in purus eu justo sodales lacinia. Maecenas feugiat justo a sem convallis viverra. Donec a gravida sem, eu maximus leo. Integer quis ex vitae velit auctor tincidunt. Curabitur ut velit eros. Nunc efficitur accumsan dictum. Vestibulum vehicula nulla nec erat ultrices, ut varius massa rutrum. Integer vehicula, ipsum sed laoreet euismod, orci nulla euismod eros, eget pulvinar arcu lacus in odio. Nam a ligula luctus, consectetur arcu nec, egestas ante. Donec in vulputate diam. Sed porta odio et gravida cursus. Sed ut pharetra leo.\nSuspendisse a malesuada dolor, sit amet bibendum risus. Donec ut porttitor massa. Sed faucibus congue ipsum quis efficitur. Suspendisse posuere malesuada posuere. Nulla commodo erat et cursus vehicula. Quisque tempor metus ac turpis placerat tempor. Fusce ex leo, aliquam vitae rutrum ut, mattis eget purus. Nunc a aliquet enim. Praesent tincidunt sollicitudin tincidunt. Duis luctus ligula urna, sed tincidunt est semper nec. Suspendisse potenti. Duis nec dolor feugiat, commodo ipsum non, hendrerit quam.\nMorbi quis fringilla erat. Proin pharetra tortor quis enim facilisis auctor. Vestibulum eget ultricies diam, sed tristique odio. Nulla nibh diam, congue nec viverra a, rutrum sit amet magna. Sed ac velit sed mauris volutpat tincidunt. Aliquam malesuada risus ac lectus tristique, vitae cursus eros pulvinar. Etiam sit amet erat semper, bibendum quam sed, porttitor justo.\nMaecenas mi quam, euismod at ullamcorper ut, commodo at quam. Morbi dictum ligula ut malesuada tincidunt. Proin volutpat, urna sit amet commodo imperdiet, diam urna bibendum dui, non finibus leo diam id eros. Quisque iaculis massa et massa feugiat auctor. Vivamus nec accumsan magna. Quisque in interdum eros. Praesent dolor massa, convallis id pharetra eu, congue et eros. Proin facilisis vehicula sapien dignissim condimentum.\nPhasellus non mi ut ante pretium congue ut vel lacus. Suspendisse potenti. Etiam quis justo laoreet, porttitor quam eget, varius nunc. Nam quis tortor enim. Nunc vehicula a erat vitae semper. Aliquam laoreet dignissim feugiat. Morbi eleifend cursus suscipit. Proin vestibulum vestibulum nibh, sed egestas nibh luctus eget. Sed facilisis eros luctus, volutpat sem at, porttitor felis. Nam placerat eleifend leo et tempor. Proin a ligula eleifend erat hendrerit suscipit a et magna. Suspendisse potenti. Quisque sollicitudin turpis sed ornare euismod. Aliquam molestie sed magna id volutpat. Nullam at cursus lacus, id consectetur nulla. Fusce rutrum laoreet ligula tempor dignissim."
  },
  {
    "id": 4,
    "date": 20250802,
    "title": "Vestibulum dignissim, magna ac luctus dignissim.",
    "content": "Ut ornare et urna sed vehicula. Duis non egestas libero. Phasellus dolor nulla, viverra ut ex eget, posuere eleifend purus. Morbi neque nunc, sagittis eget iaculis sit amet, condimentum quis lorem. Aenean eu lorem lorem. Vestibulum ante ipsum primis in faucibus orci luctus et ultrices posuere cubilia curae; Nulla tellus purus, venenatis vel ante vitae, sollicitudin vehicula nisl. Suspendisse condimentum molestie ligula et finibus. Donec erat elit, mollis et quam nec, pretium efficitur purus. Phasellus erat dui, volutpat quis urna in, ornare aliquam libero. Proin efficitur non sapien ac aliquam.\nSuspendisse varius aliquam lorem ut feugiat. Phasellus at nisl tristique, tempor ante at, interdum mi. Sed vel nulla est. Donec porttitor varius porttitor. Phasellus fermentum, mauris et iaculis aliquam, arcu nulla tincidunt leo, hendrerit laoreet massa est sit amet purus. Vestibulum vulputate volutpat pellentesque. Maecenas varius ultrices lorem. In hac habitasse platea dictumst. Vivamus vestibulum sed nulla ut scelerisque.\nFusce pulvinar, quam id interdum pretium, arcu mauris maximus nibh, ut malesuada arcu nunc ut justo. Suspendisse molestie consequat diam, quis lobortis lacus aliquam facilisis. Sed risus erat, ullamcorper vel tincidunt nec, sodales et erat. Ut fringilla posuere nisl mollis rutrum. Nullam vitae feugiat tellus, sit amet pretium quam. Suspendisse malesuada dapibus mauris, ac gravida ex. Aliquam at rutrum odio. Suspendisse commodo massa sit amet massa pellentesque congue. In rhoncus fermentum risus sed consequat. Duis et felis ut ipsum commodo tristique rutrum non ipsum. Phasellus placerat ac neque a blandit. Sed vel ornare magna, quis feugiat odio. Phasellus aliquam lorem quis aliquam finibus. Duis vestibulum in sem iaculis iaculis.\nPhasellus pulvinar enim sed convallis dignissim. Nunc dictum urna dolor, in pellentesque mi efficitur ut. Maecenas id justo et orci placerat ultricies blandit eu nibh. Nunc non vehicula ex, porttitor aliquet enim. Quisque eu erat tincidunt, malesuada orci vel, convallis purus. Nulla molestie egestas fringilla. Donec id eros id tellus molestie interdum a eget urna. Etiam placerat, nibh et tristique ultricies, augue odio consequat diam, id rutrum nibh tortor ac felis. Praesent ac consectetur enim. Aenean ultricies felis viverra ipsum mattis, ut auctor nunc lacinia. Quisque at pulvinar nulla. Cras quis diam ac arcu ornare aliquet. Integer at lectus eu lorem iaculis luctus sed eget risus. Curabitur accumsan quam ante, eu luctus neque pulvinar sit amet. Vestibulum rhoncus tincidunt volutpat. Ut mollis nisl leo, id pretium tortor sollicitudin non.\nNulla lectus neque, iaculis et commodo eu, ultricies vitae lectus. Ut in dolor interdum, eleifend turpis ac, auctor augue. Praesent at dapibus sem. Fusce et dui eu nunc feugiat porta vitae eget leo. Integer a efficitur risus, ac dictum sapien. Ut magna purus, sodales et consectetur eget, luctus ac est. Praesent ultrices arcu at magna tincidunt egestas. Mauris luctus semper enim at consectetur. Vestibulum et auctor mauris, ac mattis libero. Nam eu rutrum purus. Integer vel tellus vel turpis malesuada pharetra non eu massa. Duis molestie orci accumsan lectus congue, vel ullamcorper metus gravida. Sed vitae luctus velit. Cras dolor risus, luctus nec imperdiet vel, egestas a mi."
  },
  {
    "id": 5,
    "date": 20250829,
    "title": "Ut in egestas tellus.",
    "content": "Ut ornare et urna sed vehicula. Duis non egestas libero. Phasellus dolor nulla, viverra ut ex eget, posuere eleifend purus. Morbi neque nunc, sagittis eget iaculis sit amet, condimentum quis lorem. Aenean eu lorem lorem. Vestibulum ante ipsum primis in faucibus orci luctus et ultrices posuere cubilia curae; Nulla tellus purus, venenatis vel ante vitae, sollicitudin vehicula nisl. Suspendisse condimentum molestie ligula et finibus. Donec erat elit, mollis et quam nec, pretium efficitur purus. Phasellus erat dui, volutpat quis urna in, ornare aliquam libero. Proin efficitur non sapien ac aliquam.\nSuspendisse varius aliquam lorem ut feugiat. Phasellus at nisl tristique, tempor ante at, interdum mi. Sed vel nulla est. Donec porttitor varius porttitor. Phasellus fermentum, mauris et iaculis aliquam, arcu nulla tincidunt leo, hendrerit laoreet massa est sit amet purus. Vestibulum vulputate volutpat pellentesque. Maecenas varius ultrices lorem. In hac habitasse platea dictumst. Vivamus vestibulum sed nulla ut scelerisque.\nFusce pulvinar, quam id interdum pretium, arcu mauris maximus nibh, ut malesuada arcu nunc ut justo. Suspendisse molestie consequat diam, quis lobortis lacus aliquam facilisis. Sed risus erat, ullamcorper vel tincidunt nec, sodales et erat. Ut fringilla posuere nisl mollis rutrum. Nullam vitae feugiat tellus, sit amet pretium quam. Suspendisse malesuada dapibus mauris, ac gravida ex. Aliquam at rutrum odio. Suspendisse commodo massa sit amet massa pellentesque congue. In rhoncus fermentum risus sed consequat. Duis et felis ut ipsum commodo tristique rutrum non ipsum. Phasellus placerat ac neque a blandit. Sed vel ornare magna, quis feugiat odio. Phasellus aliquam lorem quis aliquam finibus. Duis vestibulum in sem iaculis iaculis.\nPhasellus pulvinar enim sed convallis dignissim. Nunc dictum urna dolor, in pellentesque mi efficitur ut. Maecenas id justo et orci placerat ultricies blandit eu nibh. Nunc non vehicula ex, porttitor aliquet enim. Quisque eu erat tincidunt, malesuada orci vel, convallis purus. Nulla molestie egestas fringilla. Donec id eros id tellus molestie interdum a eget urna. Etiam placerat, nibh et tristique ultricies, augue odio consequat diam, id rutrum nibh tortor ac felis. Praesent ac consectetur enim. Aenean ultricies felis viverra ipsum mattis, ut auctor nunc lacinia. Quisque at pulvinar nulla. Cras quis diam ac arcu ornare aliquet. Integer at lectus eu lorem iaculis luctus sed eget risus. Curabitur accumsan quam ante, eu luctus neque pulvinar sit amet. Vestibulum rhoncus tincidunt volutpat. Ut mollis nisl leo, id pretium tortor sollicitudin non.\nNulla lectus neque, iaculis et commodo eu, ultricies vitae lectus. Ut in dolor interdum, eleifend turpis ac, auctor augue. Praesent at dapibus sem. Fusce et dui eu nunc feugiat porta vitae eget leo. Integer a efficitur risus, ac dictum sapien. Ut magna purus, sodales et consectetur eget, luctus ac est. Praesent ultrices arcu at magna tincidunt egestas. Mauris luctus semper enim at consectetur. Vestibulum et auctor mauris, ac mattis libero. Nam eu rutrum purus. Integer vel tellus vel turpis malesuada pharetra non eu massa. Duis molestie orci accumsan lectus congue, vel ullamcorper metus gravida. Sed vitae luctus velit. Cras dolor risus, luctus nec imperdiet vel, egestas a mi."
  }
]